mcp2210/__init__.py
mcp2210/mcp2210.py
mcp2210/validated_dataclass.py
mcp2210_python-1.0.8.dist-info/LICENSE
mcp2210_python-1.0.8.dist-info/METADATA
mcp2210_python-1.0.8.dist-info/WHEEL
mcp2210_python-1.0.8.dist-info/top_level.txt
mcp2210_python-1.0.8.dist-info/RECORD
