Metadata-Version: 2.1
Name: mcp2210-python
Version: 1.0.8
Summary: A python driver for the MCP2210 USB-to-SPI converter
Home-page: https://github.com/jeremyherbert/mcp2210-python
Author: Jeremy Herbert
Author-email: jeremy.006@gmail.com
Classifier: Programming Language :: Python :: 3
Classifier: License :: OSI Approved :: MIT License
Classifier: Operating System :: OS Independent
Requires-Python: >=3.8
License-File: LICENSE
Requires-Dist: hidapi
